<?xml version="1.0" encoding="UTF-8" standalone="no"?>
<event category="CREATE" id="0">
  <actions>
    <action id="603" library="1">
      <!--action name: Code-->
      <kind>CODE</kind>
      <allowRelative>false</allowRelative>
      <question>false</question>
      <canApplyTo>true</canApplyTo>
      <actionType>CODE</actionType>
      <functionName/>
      <relative>false</relative>
      <not>false</not>
      <appliesTo>.self</appliesTo>
      <arguments>
        <argument kind="STRING">//Shape
shapex[0]=-104;
shapey[0]=16;
shapex[1]=-77;
shapey[1]=81;
shapex[2]=-62;
shapey[2]=74;
shapex[3]=-82;
shapey[3]=26;
shapex[4]=4;
shapey[4]=-30;
points=5;
bone=5;

scr_findallangles();</argument>
      </arguments>
    </action>
  </actions>
</event>
