<?xml version="1.0" encoding="UTF-8" standalone="no"?>
<event category="CREATE" id="0">
  <actions>
    <action id="603" library="1">
      <!--action name: Code-->
      <kind>CODE</kind>
      <allowRelative>false</allowRelative>
      <question>false</question>
      <canApplyTo>true</canApplyTo>
      <actionType>CODE</actionType>
      <functionName/>
      <relative>false</relative>
      <not>false</not>
      <appliesTo>.self</appliesTo>
      <arguments>
        <argument kind="STRING">x1=xstart;
y1=ystart;
x2=xstart+25;
y2=ystart+25;
x3=xstart+50;
y3=ystart+50;
x4=xstart+75;
y4=ystart+75;
</argument>
      </arguments>
    </action>
  </actions>
</event>
