<?xml version="1.0" encoding="UTF-8" standalone="no"?>
<event category="CREATE" id="0">
  <actions>
    <action id="603" library="1">
      <!--action name: Code-->
      <kind>CODE</kind>
      <allowRelative>false</allowRelative>
      <question>false</question>
      <canApplyTo>true</canApplyTo>
      <actionType>CODE</actionType>
      <functionName/>
      <relative>false</relative>
      <not>false</not>
      <appliesTo>.self</appliesTo>
      <arguments>
        <argument kind="STRING">{
alarm[1]=90;
gravity=0.8;
gravity_direction=270;
image_speed=random(4)-2;
image_index=floor(random(4));
rand=random(3);
if (rand&gt;1)
    sprite_index=spr_scrapbrown2;
if (rand&gt;2)
    sprite_index=spr_scrapbrown3;
}</argument>
      </arguments>
    </action>
  </actions>
</event>
